<library>
  <meshfact name="he_hangdao02_mesh_ercaibiand_775">
    <plugin>genmeshfact</plugin>
    <zuse />
    <params>
      <material>Material_JoinedMaterial_#140_he_hangdao02</material>
      <v x="-10.9611" y="1.4759" z="-19.6222" u="0.2703" v="-2.408" nx="0.9659" ny="-0.0001" nz="-0.2588" />
      <v x="-10.961" y="2.5876" z="-19.6222" u="0.9556" v="-2.408" nx="0.9659" ny="-0.0001" nz="-0.2588" />
      <v x="-10.7811" y="2.5876" z="-18.9509" u="0.9556" v="0.9482" nx="0.9659" ny="-0.0001" nz="-0.2588" />
      <t v1="0" v2="1" v3="2" />
      <v x="-10.7811" y="2.5876" z="-18.9509" u="0.9556" v="0.9482" nx="0.9659" ny="-0.0001" nz="-0.2587" />
      <v x="-10.7812" y="1.4758" z="-18.9509" u="0.2703" v="0.9482" nx="0.9659" ny="-0.0001" nz="-0.2587" />
      <v x="-10.9611" y="1.4759" z="-19.6222" u="0.2703" v="-2.408" nx="0.9659" ny="-0.0001" nz="-0.2587" />
      <t v1="3" v2="4" v3="5" />
      <v x="-10.7812" y="1.4758" z="-18.9509" u="0.2703" v="0.9482" nx="0.9659" ny="-0.0001" nz="0.2588" />
      <v x="-10.7811" y="2.5876" z="-18.9509" u="0.9556" v="0.9482" nx="0.9659" ny="-0.0001" nz="0.2588" />
      <v x="-10.961" y="2.5877" z="-18.2797" u="0.9556" v="4.3043" nx="0.9659" ny="-0.0001" nz="0.2588" />
      <t v1="6" v2="7" v3="8" />
      <v x="-10.961" y="2.5876" z="-19.6222" u="0.9556" v="-2.408" nx="0.7071" ny="0" nz="-0.7072" />
      <v x="-10.9611" y="1.4759" z="-19.6222" u="0.2703" v="-2.408" nx="0.7071" ny="0" nz="-0.7072" />
      <v x="-11.4525" y="1.4762" z="-20.1135" u="0.2703" v="-4.8649" nx="0.7071" ny="0" nz="-0.7072" />
      <t v1="9" v2="10" v3="11" />
      <v x="-11.4524" y="2.5879" z="-20.1135" u="0.9556" v="-4.8649" nx="0.7071" ny="0" nz="-0.7072" />
      <t v1="11" v2="12" v3="9" />
      <v x="-10.961" y="2.5877" z="-18.2797" u="0.9556" v="4.3043" nx="0.9659" ny="-0.0001" nz="0.2587" />
      <v x="-10.9611" y="1.476" z="-18.2797" u="0.2703" v="4.3044" nx="0.9659" ny="-0.0001" nz="0.2587" />
      <v x="-10.7812" y="1.4758" z="-18.9509" u="0.2703" v="0.9482" nx="0.9659" ny="-0.0001" nz="0.2587" />
      <t v1="13" v2="14" v3="15" />
      <v x="-12.1237" y="1.4766" z="-20.2933" u="0.2703" v="0.9482" nx="0.2588" ny="0" nz="-0.9659" />
      <v x="-12.1236" y="2.5883" z="-20.2933" u="0.9556" v="0.9482" nx="0.2588" ny="0" nz="-0.9659" />
      <v x="-11.4524" y="2.5879" z="-20.1135" u="0.9556" v="4.3043" nx="0.2588" ny="0" nz="-0.9659" />
      <t v1="16" v2="17" v3="18" />
      <v x="-11.4525" y="1.4762" z="-20.1135" u="0.2703" v="4.3043" nx="0.2588" ny="0" nz="-0.9659" />
      <t v1="18" v2="19" v3="16" />
      <v x="-12.1236" y="2.5883" z="-20.2933" u="0.9556" v="0.9482" nx="-0.2587" ny="0" nz="-0.9659" />
      <v x="-12.1237" y="1.4766" z="-20.2933" u="0.2703" v="0.9482" nx="-0.2587" ny="0" nz="-0.9659" />
      <v x="-12.7949" y="1.4771" z="-20.1135" u="0.2703" v="-2.408" nx="-0.2587" ny="0" nz="-0.9659" />
      <t v1="20" v2="21" v3="22" />
      <v x="-12.7949" y="1.4771" z="-20.1135" u="0.2703" v="-2.408" nx="-0.2588" ny="0" nz="-0.9659" />
      <v x="-12.7948" y="2.5888" z="-20.1135" u="0.9556" v="-2.408" nx="-0.2588" ny="0" nz="-0.9659" />
      <v x="-12.1236" y="2.5883" z="-20.2933" u="0.9556" v="0.9482" nx="-0.2588" ny="0" nz="-0.9659" />
      <t v1="23" v2="24" v3="25" />
      <v x="-12.7948" y="2.5888" z="-20.1135" u="0.9556" v="-2.408" nx="-0.7071" ny="0.0001" nz="-0.7072" />
      <v x="-12.7949" y="1.4771" z="-20.1135" u="0.2703" v="-2.408" nx="-0.7071" ny="0.0001" nz="-0.7072" />
      <v x="-13.2863" y="1.4775" z="-19.6222" u="0.2703" v="-4.8649" nx="-0.7071" ny="0.0001" nz="-0.7072" />
      <t v1="26" v2="27" v3="28" />
      <v x="-13.2862" y="2.5892" z="-19.6222" u="0.9556" v="-4.8649" nx="-0.7071" ny="0.0001" nz="-0.7072" />
      <t v1="28" v2="29" v3="26" />
      <v x="-13.4661" y="1.4776" z="-18.9509" u="0.2703" v="0.9482" nx="-0.9659" ny="0.0001" nz="-0.2588" />
      <v x="-13.4661" y="2.5894" z="-18.9509" u="0.9556" v="0.9482" nx="-0.9659" ny="0.0001" nz="-0.2588" />
      <v x="-13.2862" y="2.5892" z="-19.6222" u="0.9556" v="4.3043" nx="-0.9659" ny="0.0001" nz="-0.2588" />
      <t v1="30" v2="31" v3="32" />
      <v x="-13.2862" y="2.5892" z="-19.6222" u="0.9556" v="4.3043" nx="-0.9659" ny="0.0001" nz="-0.2587" />
      <v x="-13.2863" y="1.4775" z="-19.6222" u="0.2703" v="4.3043" nx="-0.9659" ny="0.0001" nz="-0.2587" />
      <v x="-13.4661" y="1.4776" z="-18.9509" u="0.2703" v="0.9482" nx="-0.9659" ny="0.0001" nz="-0.2587" />
      <t v1="33" v2="34" v3="35" />
      <v x="-13.4661" y="2.5894" z="-18.9509" u="0.9556" v="0.9482" nx="-0.9659" ny="0.0001" nz="0.2587" />
      <v x="-13.4661" y="1.4776" z="-18.9509" u="0.2703" v="0.9482" nx="-0.9659" ny="0.0001" nz="0.2587" />
      <v x="-13.2863" y="1.4776" z="-18.2797" u="0.2703" v="-2.408" nx="-0.9659" ny="0.0001" nz="0.2587" />
      <t v1="36" v2="37" v3="38" />
      <v x="-13.2863" y="1.4776" z="-18.2797" u="0.2703" v="-2.408" nx="-0.9659" ny="0.0001" nz="0.2588" />
      <v x="-13.2862" y="2.5893" z="-18.2797" u="0.9556" v="-2.408" nx="-0.9659" ny="0.0001" nz="0.2588" />
      <v x="-13.4661" y="2.5894" z="-18.9509" u="0.9556" v="0.9482" nx="-0.9659" ny="0.0001" nz="0.2588" />
      <t v1="39" v2="40" v3="41" />
      <v x="-13.2862" y="2.5893" z="-18.2797" u="0.9556" v="-2.408" nx="-0.7071" ny="0.0001" nz="0.7072" />
      <v x="-13.2863" y="1.4776" z="-18.2797" u="0.2703" v="-2.408" nx="-0.7071" ny="0.0001" nz="0.7072" />
      <v x="-12.7949" y="1.4773" z="-17.7883" u="0.2703" v="-4.8649" nx="-0.7071" ny="0.0001" nz="0.7072" />
      <t v1="42" v2="43" v3="44" />
      <v x="-12.7948" y="2.589" z="-17.7883" u="0.9556" v="-4.8649" nx="-0.7071" ny="0.0001" nz="0.7072" />
      <t v1="44" v2="45" v3="42" />
      <v x="-12.1237" y="1.4768" z="-17.6084" u="0.2703" v="0.9482" nx="-0.2588" ny="0.0001" nz="0.9659" />
      <v x="-12.1236" y="2.5886" z="-17.6085" u="0.9556" v="0.9482" nx="-0.2588" ny="0.0001" nz="0.9659" />
      <v x="-12.7948" y="2.589" z="-17.7883" u="0.9556" v="4.3043" nx="-0.2588" ny="0.0001" nz="0.9659" />
      <t v1="46" v2="47" v3="48" />
      <v x="-12.7948" y="2.589" z="-17.7883" u="0.9556" v="4.3043" nx="-0.2589" ny="0" nz="0.9659" />
      <v x="-12.7949" y="1.4773" z="-17.7883" u="0.2703" v="4.3044" nx="-0.2589" ny="0" nz="0.9659" />
      <v x="-12.1237" y="1.4768" z="-17.6084" u="0.2703" v="0.9482" nx="-0.2589" ny="0" nz="0.9659" />
      <t v1="49" v2="50" v3="51" />
      <v x="-12.1236" y="2.5886" z="-17.6085" u="0.9556" v="0.9482" nx="0.2589" ny="0.0001" nz="0.9659" />
      <v x="-12.1237" y="1.4768" z="-17.6084" u="0.2703" v="0.9482" nx="0.2589" ny="0.0001" nz="0.9659" />
      <v x="-11.4525" y="1.4764" z="-17.7883" u="0.2703" v="-2.408" nx="0.2589" ny="0.0001" nz="0.9659" />
      <t v1="52" v2="53" v3="54" />
      <v x="-11.4525" y="1.4764" z="-17.7883" u="0.2703" v="-2.408" nx="0.2588" ny="0" nz="0.9659" />
      <v x="-11.4524" y="2.5881" z="-17.7883" u="0.9556" v="-2.408" nx="0.2588" ny="0" nz="0.9659" />
      <v x="-12.1236" y="2.5886" z="-17.6085" u="0.9556" v="0.9482" nx="0.2588" ny="0" nz="0.9659" />
      <t v1="55" v2="56" v3="57" />
      <v x="-11.4524" y="2.5881" z="-17.7883" u="0.9556" v="-2.408" nx="0.7071" ny="0" nz="0.7072" />
      <v x="-11.4525" y="1.4764" z="-17.7883" u="0.2703" v="-2.408" nx="0.7071" ny="0" nz="0.7072" />
      <v x="-10.9611" y="1.476" z="-18.2797" u="0.2703" v="-4.8649" nx="0.7071" ny="0" nz="0.7072" />
      <t v1="58" v2="59" v3="60" />
      <v x="-10.961" y="2.5877" z="-18.2797" u="0.9556" v="-4.8649" nx="0.7071" ny="0" nz="0.7072" />
      <t v1="60" v2="61" v3="58" />
      <v x="-11.1403" y="1.5824" z="-19.5187" u="0.8023" v="3.7867" nx="-0.9659" ny="0.0011" nz="0.2588" />
      <v x="-11.1404" y="1.476" z="-19.5187" u="0.2703" v="3.7867" nx="-0.9659" ny="0.0011" nz="0.2588" />
      <v x="-10.9883" y="1.476" z="-18.9509" u="0.2703" v="0.9482" nx="-0.9659" ny="0.0011" nz="0.2588" />
      <t v1="62" v2="63" v3="64" />
      <v x="-10.9882" y="1.5824" z="-18.9509" u="0.8023" v="0.9482" nx="-0.9659" ny="0.0011" nz="0.2588" />
      <t v1="64" v2="65" v3="62" />
      <v x="-10.9882" y="1.5824" z="-18.9509" u="0.8023" v="0.9482" nx="-0.9659" ny="0.0011" nz="-0.2588" />
      <v x="-10.9883" y="1.476" z="-18.9509" u="0.2703" v="0.9482" nx="-0.9659" ny="0.0011" nz="-0.2588" />
      <v x="-11.1404" y="1.4761" z="-18.3832" u="0.2703" v="-1.8903" nx="-0.9659" ny="0.0011" nz="-0.2588" />
      <t v1="66" v2="67" v3="68" />
      <v x="-11.1404" y="1.476" z="-19.5187" u="0.2703" v="3.7867" nx="-0.7071" ny="0.0008" nz="0.7072" />
      <v x="-11.1403" y="1.5824" z="-19.5187" u="0.8023" v="3.7867" nx="-0.7071" ny="0.0008" nz="0.7072" />
      <v x="-11.5558" y="1.5827" z="-19.9342" u="0.8023" v="5.8647" nx="-0.7071" ny="0.0008" nz="0.7072" />
      <t v1="69" v2="70" v3="71" />
      <v x="-11.556" y="1.4763" z="-19.9342" u="0.2703" v="5.8647" nx="-0.7071" ny="0.0008" nz="0.7072" />
      <t v1="71" v2="72" v3="69" />
      <v x="-11.1403" y="1.5825" z="-18.3832" u="0.8023" v="-1.8903" nx="-0.9659" ny="0.0011" nz="-0.2588" />
      <t v1="68" v2="73" v3="66" />
      <v x="-12.1236" y="1.5831" z="-20.0863" u="0.8023" v="0.948" nx="-0.2588" ny="0.0001" nz="0.9659" />
      <v x="-12.1237" y="1.4767" z="-20.0863" u="0.2703" v="0.9482" nx="-0.2588" ny="0.0001" nz="0.9659" />
      <v x="-11.556" y="1.4763" z="-19.9342" u="0.2703" v="-1.8903" nx="-0.2588" ny="0.0001" nz="0.9659" />
      <t v1="74" v2="75" v3="76" />
      <v x="-11.556" y="1.4763" z="-19.9342" u="0.2703" v="-1.8903" nx="-0.2588" ny="0.0003" nz="0.9659" />
      <v x="-11.5558" y="1.5827" z="-19.9342" u="0.8023" v="-1.8906" nx="-0.2588" ny="0.0003" nz="0.9659" />
      <v x="-12.1236" y="1.5831" z="-20.0863" u="0.8023" v="0.948" nx="-0.2588" ny="0.0003" nz="0.9659" />
      <t v1="77" v2="78" v3="79" />
      <v x="-12.1237" y="1.4767" z="-20.0863" u="0.2703" v="0.9482" nx="0.2588" ny="-0.0001" nz="0.9659" />
      <v x="-12.1236" y="1.5831" z="-20.0863" u="0.8023" v="0.948" nx="0.2588" ny="-0.0001" nz="0.9659" />
      <v x="-12.6913" y="1.5835" z="-19.9342" u="0.8023" v="3.7865" nx="0.2588" ny="-0.0001" nz="0.9659" />
      <t v1="80" v2="81" v3="82" />
      <v x="-12.6913" y="1.5835" z="-19.9342" u="0.8023" v="3.7865" nx="0.2588" ny="-0.0003" nz="0.9659" />
      <v x="-12.6914" y="1.477" z="-19.9342" u="0.2703" v="3.7867" nx="0.2588" ny="-0.0003" nz="0.9659" />
      <v x="-12.1237" y="1.4767" z="-20.0863" u="0.2703" v="0.9482" nx="0.2588" ny="-0.0003" nz="0.9659" />
      <t v1="83" v2="84" v3="85" />
      <v x="-12.6914" y="1.477" z="-19.9342" u="0.2703" v="3.7867" nx="0.7071" ny="-0.0008" nz="0.7072" />
      <v x="-12.6913" y="1.5835" z="-19.9342" u="0.8023" v="3.7865" nx="0.7071" ny="-0.0008" nz="0.7072" />
      <v x="-13.1069" y="1.5838" z="-19.5187" u="0.8023" v="5.8644" nx="0.7071" ny="-0.0008" nz="0.7072" />
      <t v1="86" v2="87" v3="88" />
      <v x="-13.107" y="1.4774" z="-19.5187" u="0.2703" v="5.8647" nx="0.7071" ny="-0.0008" nz="0.7072" />
      <t v1="88" v2="89" v3="86" />
      <v x="-13.259" y="1.5839" z="-18.9509" u="0.8023" v="0.9482" nx="0.9659" ny="-0.0011" nz="0.2588" />
      <v x="-13.2591" y="1.4775" z="-18.9509" u="0.2703" v="0.9482" nx="0.9659" ny="-0.0011" nz="0.2588" />
      <v x="-13.107" y="1.4774" z="-19.5187" u="0.2703" v="-1.8903" nx="0.9659" ny="-0.0011" nz="0.2588" />
      <t v1="90" v2="91" v3="92" />
      <v x="-13.1069" y="1.5838" z="-19.5187" u="0.8023" v="-1.8904" nx="0.9659" ny="-0.0011" nz="0.2588" />
      <t v1="92" v2="93" v3="90" />
      <v x="-13.2591" y="1.4775" z="-18.9509" u="0.2703" v="0.9482" nx="0.9659" ny="-0.0011" nz="-0.2588" />
      <v x="-13.259" y="1.5839" z="-18.9509" u="0.8023" v="0.9482" nx="0.9659" ny="-0.0011" nz="-0.2588" />
      <v x="-13.1069" y="1.5838" z="-18.3832" u="0.8023" v="3.7867" nx="0.9659" ny="-0.0011" nz="-0.2588" />
      <t v1="94" v2="95" v3="96" />
      <v x="-13.107" y="1.4774" z="-18.3832" u="0.2703" v="3.7867" nx="0.9659" ny="-0.0011" nz="-0.2588" />
      <t v1="96" v2="97" v3="94" />
      <v x="-13.107" y="1.4774" z="-18.3832" u="0.2703" v="3.7867" nx="0.7071" ny="-0.0008" nz="-0.7072" />
      <v x="-13.1069" y="1.5838" z="-18.3832" u="0.8023" v="3.7867" nx="0.7071" ny="-0.0008" nz="-0.7072" />
      <v x="-12.6913" y="1.5836" z="-17.9677" u="0.8023" v="5.8646" nx="0.7071" ny="-0.0008" nz="-0.7072" />
      <t v1="98" v2="99" v3="100" />
      <v x="-12.6914" y="1.4772" z="-17.9677" u="0.2703" v="5.8647" nx="0.7071" ny="-0.0008" nz="-0.7072" />
      <t v1="100" v2="101" v3="98" />
      <v x="-12.1236" y="1.5832" z="-17.8156" u="0.8023" v="0.9484" nx="0.2588" ny="-0.0001" nz="-0.9659" />
      <v x="-12.1237" y="1.4768" z="-17.8156" u="0.2703" v="0.9482" nx="0.2588" ny="-0.0001" nz="-0.9659" />
      <v x="-12.6914" y="1.4772" z="-17.9677" u="0.2703" v="-1.8903" nx="0.2588" ny="-0.0001" nz="-0.9659" />
      <t v1="102" v2="103" v3="104" />
      <v x="-12.6914" y="1.4772" z="-17.9677" u="0.2703" v="-1.8903" nx="0.2588" ny="-0.0003" nz="-0.9659" />
      <v x="-12.6913" y="1.5836" z="-17.9677" u="0.8023" v="-1.8901" nx="0.2588" ny="-0.0003" nz="-0.9659" />
      <v x="-12.1236" y="1.5832" z="-17.8156" u="0.8023" v="0.9484" nx="0.2588" ny="-0.0003" nz="-0.9659" />
      <t v1="105" v2="106" v3="107" />
      <v x="-12.1237" y="1.4768" z="-17.8156" u="0.2703" v="0.9482" nx="-0.2588" ny="0.0001" nz="-0.9659" />
      <v x="-12.1236" y="1.5832" z="-17.8156" u="0.8023" v="0.9484" nx="-0.2588" ny="0.0001" nz="-0.9659" />
      <v x="-11.5558" y="1.5828" z="-17.9677" u="0.8023" v="3.7869" nx="-0.2588" ny="0.0001" nz="-0.9659" />
      <t v1="108" v2="109" v3="110" />
      <v x="-11.5558" y="1.5828" z="-17.9677" u="0.8023" v="3.7869" nx="-0.2588" ny="0.0003" nz="-0.9659" />
      <v x="-11.556" y="1.4764" z="-17.9677" u="0.2703" v="3.7867" nx="-0.2588" ny="0.0003" nz="-0.9659" />
      <v x="-12.1237" y="1.4768" z="-17.8156" u="0.2703" v="0.9482" nx="-0.2588" ny="0.0003" nz="-0.9659" />
      <t v1="111" v2="112" v3="113" />
      <v x="-11.556" y="1.4764" z="-17.9677" u="0.2703" v="3.7867" nx="-0.7071" ny="0.0008" nz="-0.7072" />
      <v x="-11.5558" y="1.5828" z="-17.9677" u="0.8023" v="3.7869" nx="-0.7071" ny="0.0008" nz="-0.7072" />
      <v x="-11.1403" y="1.5825" z="-18.3832" u="0.8023" v="5.8649" nx="-0.7071" ny="0.0008" nz="-0.7072" />
      <t v1="114" v2="115" v3="116" />
      <v x="-11.1404" y="1.4761" z="-18.3832" u="0.2703" v="5.8647" nx="-0.7071" ny="0.0008" nz="-0.7072" />
      <t v1="116" v2="117" v3="114" />
    </params>
  </meshfact>
</library>
