<library>
  <meshfact name="he_hangdao_mesh_ercaihangd_1188">
    <plugin>genmeshfact</plugin>
    <zuse />
    <params>
      <material>Material_u_0265_he_hangdao</material>
      <v x="72.8936" y="8.939" z="299.8132" u="0.4667" v="0.8801" nx="-1" ny="0.0055" nz="0.003" />
      <v x="72.8978" y="9.6921" z="299.8132" u="0.4667" v="0.6097" nx="-1" ny="0.0055" nz="0.003" />
      <v x="72.8925" y="9.6331" z="298.1677" u="0.984" v="0.6078" nx="-1" ny="0.0055" nz="0.003" />
      <t v1="0" v2="1" v3="2" />
      <v x="72.8925" y="9.6331" z="298.1677" u="0.984" v="0.6078" nx="-0.9999" ny="-0.0106" nz="-0.0038" />
      <v x="72.9007" y="8.8438" z="298.1981" u="0.984" v="0.8619" nx="-0.9999" ny="-0.0106" nz="-0.0038" />
      <v x="72.8936" y="8.939" z="299.8132" u="0.4667" v="0.8801" nx="-0.9999" ny="-0.0106" nz="-0.0038" />
      <t v1="3" v2="4" v3="5" />
      <v x="72.8927" y="10.6465" z="298.3496" u="0.8779" v="0.2845" nx="-1" ny="-0.0003" nz="0.0032" />
      <v x="72.8925" y="9.6331" z="298.1677" u="0.984" v="0.6078" nx="-1" ny="-0.0003" nz="0.0032" />
      <v x="72.8978" y="9.6921" z="299.8132" u="0.4667" v="0.6097" nx="-1" ny="-0.0003" nz="0.0032" />
      <t v1="6" v2="7" v3="8" />
      <v x="72.8857" y="10.6449" z="299.8132" u="0.4667" v="0.3177" nx="-0.9999" ny="-0.0127" nz="-0.0017" />
      <v x="72.8978" y="9.6921" z="299.8132" u="0.4667" v="0.6097" nx="-0.9999" ny="-0.0127" nz="-0.0017" />
      <v x="72.8916" y="9.8067" z="302.5463" u="-0.0128" v="0.6075" nx="-0.9999" ny="-0.0127" nz="-0.0017" />
      <t v1="9" v2="10" v3="11" />
      <v x="72.8978" y="9.6921" z="299.8132" u="0.4667" v="0.6097" nx="-0.9999" ny="-0.0127" nz="-0.0048" />
      <v x="72.8857" y="10.6449" z="299.8132" u="0.4667" v="0.3177" nx="-0.9999" ny="-0.0127" nz="-0.0048" />
      <v x="72.8927" y="10.6465" z="298.3496" u="0.8779" v="0.2845" nx="-0.9999" ny="-0.0127" nz="-0.0048" />
      <t v1="12" v2="13" v3="14" />
      <v x="72.8978" y="9.6921" z="299.8132" u="0.4667" v="0.6097" nx="-1" ny="0.0055" nz="0.0019" />
      <v x="72.8936" y="8.939" z="299.8132" u="0.4667" v="0.8801" nx="-1" ny="0.0055" nz="0.0019" />
      <v x="72.8997" y="9.0804" z="302.6543" u="-0.0505" v="0.8423" nx="-1" ny="0.0055" nz="0.0019" />
      <t v1="15" v2="16" v3="17" />
      <v x="72.8997" y="9.0804" z="302.6543" u="-0.0505" v="0.8423" nx="-0.9999" ny="-0.0114" nz="-0.0018" />
      <v x="72.8916" y="9.8067" z="302.5463" u="-0.0128" v="0.6075" nx="-0.9999" ny="-0.0114" nz="-0.0018" />
      <v x="72.8978" y="9.6921" z="299.8132" u="0.4667" v="0.6097" nx="-0.9999" ny="-0.0114" nz="-0.0018" />
      <t v1="18" v2="19" v3="20" />
      <v x="72.8798" y="11.5946" z="298.5345" u="0.8141" v="0.1112" nx="-0.9999" ny="-0.0126" nz="-0.0048" />
      <v x="72.8927" y="10.6465" z="298.3496" u="0.8779" v="0.2845" nx="-0.9999" ny="-0.0126" nz="-0.0048" />
      <v x="72.8857" y="10.6449" z="299.8132" u="0.4667" v="0.3177" nx="-0.9999" ny="-0.0126" nz="-0.0048" />
      <t v1="21" v2="22" v3="23" />
      <v x="72.8809" y="11.6359" z="299.8132" u="0.4667" v="0.1128" nx="-1" ny="-0.0048" nz="-0.0002" />
      <v x="72.8857" y="10.6449" z="299.8132" u="0.4667" v="0.3177" nx="-1" ny="-0.0048" nz="-0.0002" />
      <v x="72.8849" y="10.6942" z="302.4651" u="0.0556" v="0.3213" nx="-1" ny="-0.0048" nz="-0.0002" />
      <t v1="24" v2="25" v3="26" />
      <v x="72.8857" y="10.6449" z="299.8132" u="0.4667" v="0.3177" nx="-1" ny="-0.0048" nz="0.001" />
      <v x="72.8809" y="11.6359" z="299.8132" u="0.4667" v="0.1128" nx="-1" ny="-0.0048" nz="0.001" />
      <v x="72.8798" y="11.5946" z="298.5345" u="0.8141" v="0.1112" nx="-1" ny="-0.0048" nz="0.001" />
      <t v1="27" v2="28" v3="29" />
      <v x="72.8916" y="9.8067" z="302.5463" u="-0.0128" v="0.6075" nx="-1" ny="-0.0076" nz="-0.0002" />
      <v x="72.8849" y="10.6942" z="302.4651" u="0.0556" v="0.3213" nx="-1" ny="-0.0076" nz="-0.0002" />
      <v x="72.8857" y="10.6449" z="299.8132" u="0.4667" v="0.3177" nx="-1" ny="-0.0076" nz="-0.0002" />
      <t v1="30" v2="31" v3="32" />
      <v x="72.8849" y="10.6942" z="302.4651" u="0.0556" v="0.3213" nx="-1" ny="-0.0022" nz="0.0007" />
      <v x="72.8826" y="11.6779" z="302.2996" u="0.1194" v="0.1193" nx="-1" ny="-0.0022" nz="0.0007" />
      <v x="72.8809" y="11.6359" z="299.8132" u="0.4667" v="0.1128" nx="-1" ny="-0.0022" nz="0.0007" />
      <t v1="33" v2="34" v3="35" />
      <v x="72.9025" y="8.6485" z="302.6543" u="-0.0505" v="0.9811" nx="-1" ny="-0.0065" nz="0.0025" />
      <v x="72.8997" y="9.0804" z="302.6543" u="-0.0505" v="0.8423" nx="-1" ny="-0.0065" nz="0.0025" />
      <v x="72.8936" y="8.939" z="299.8132" u="0.4667" v="0.8801" nx="-1" ny="-0.0065" nz="0.0025" />
      <t v1="36" v2="37" v3="38" />
      <v x="72.8936" y="8.939" z="299.8132" u="0.4667" v="0.8801" nx="-0.9999" ny="-0.0163" nz="0.0014" />
      <v x="72.9011" y="8.4779" z="299.8132" u="0.4667" v="0.9999" nx="-0.9999" ny="-0.0163" nz="0.0014" />
      <v x="72.9025" y="8.6485" z="302.6543" u="-0.0505" v="0.9811" nx="-0.9999" ny="-0.0163" nz="0.0014" />
      <t v1="39" v2="40" v3="41" />
      <v x="72.9016" y="8.4969" z="298.3289" u="0.984" v="0.975" nx="-0.9999" ny="-0.0163" nz="-0.0005" />
      <v x="72.9011" y="8.4779" z="299.8132" u="0.4667" v="0.9999" nx="-0.9999" ny="-0.0163" nz="-0.0005" />
      <v x="72.8936" y="8.939" z="299.8132" u="0.4667" v="0.8801" nx="-0.9999" ny="-0.0163" nz="-0.0005" />
      <t v1="42" v2="43" v3="44" />
      <v x="72.8936" y="8.939" z="299.8132" u="0.4667" v="0.8801" nx="-1" ny="-0.004" nz="-0.0041" />
      <v x="72.9007" y="8.8438" z="298.1981" u="0.984" v="0.8619" nx="-1" ny="-0.004" nz="-0.0041" />
      <v x="72.9016" y="8.4969" z="298.3289" u="0.984" v="0.975" nx="-1" ny="-0.004" nz="-0.0041" />
      <t v1="45" v2="46" v3="47" />
      <v x="34.0867" y="11.2788" z="305.229" u="0.813" v="0.2107" nx="-0.0003" ny="0.0001" nz="-1" />
      <v x="34.4473" y="11.8992" z="305.229" u="0.7622" v="0.0071" nx="-0.0003" ny="0.0001" nz="-1" />
      <v x="35.8953" y="11.9247" z="305.2286" u="0.5581" v="-0.0013" nx="-0.0003" ny="0.0001" nz="-1" />
      <t v1="48" v2="49" v3="50" />
      <v x="35.8953" y="11.9247" z="305.2286" u="0.5581" v="-0.0013" nx="-0.0002" ny="0.0001" nz="-1" />
      <v x="36.1634" y="11.0855" z="305.2285" u="0.5581" v="0.305" nx="-0.0002" ny="0.0001" nz="-1" />
      <v x="34.0867" y="11.2788" z="305.229" u="0.813" v="0.2107" nx="-0.0002" ny="0.0001" nz="-1" />
      <t v1="51" v2="52" v3="53" />
      <v x="33.5397" y="10.3292" z="305.229" u="0.8901" v="0.5223" nx="-0.0002" ny="0.0001" nz="-1" />
      <v x="34.0867" y="11.2788" z="305.229" u="0.813" v="0.2107" nx="-0.0002" ny="0.0001" nz="-1" />
      <v x="36.1634" y="11.0855" z="305.2285" u="0.5581" v="0.305" nx="-0.0002" ny="0.0001" nz="-1" />
      <t v1="54" v2="55" v3="56" />
      <v x="36.1634" y="11.0855" z="305.2285" u="0.5581" v="0.305" nx="-0.0001" ny="0.0001" nz="-1" />
      <v x="35.8953" y="11.9247" z="305.2286" u="0.5581" v="-0.0013" nx="-0.0001" ny="0.0001" nz="-1" />
      <v x="37.4302" y="11.8627" z="305.2285" u="0.3418" v="0.019" nx="-0.0001" ny="0.0001" nz="-1" />
      <t v1="57" v2="58" v3="59" />
      <v x="37.4302" y="11.8627" z="305.2285" u="0.3418" v="0.019" nx="0" ny="0" nz="-1" />
      <v x="37.6983" y="11.0234" z="305.2285" u="0.3418" v="0.3253" nx="0" ny="0" nz="-1" />
      <v x="36.1634" y="11.0855" z="305.2285" u="0.5581" v="0.305" nx="0" ny="0" nz="-1" />
      <t v1="60" v2="61" v3="62" />
      <v x="36.2338" y="10.1255" z="305.2285" u="0.5581" v="0.6259" nx="0" ny="0" nz="-1" />
      <t v1="63" v2="62" v3="61" />
      <v x="36.1634" y="11.0855" z="305.2285" u="0.5581" v="0.305" nx="-0.0002" ny="0" nz="-1" />
      <v x="36.2338" y="10.1255" z="305.2285" u="0.5581" v="0.6259" nx="-0.0002" ny="0" nz="-1" />
      <v x="33.5397" y="10.3292" z="305.229" u="0.8901" v="0.5223" nx="-0.0002" ny="0" nz="-1" />
      <t v1="64" v2="65" v3="66" />
      <v x="33.6136" y="9.4416" z="305.229" u="0.8796" v="0.8135" nx="-0.0002" ny="0" nz="-1" />
      <t v1="67" v2="66" v3="65" />
      <v x="37.7687" y="10.0635" z="305.2285" u="0.3418" v="0.6463" nx="0" ny="0" nz="-1" />
      <t v1="61" v2="68" v3="63" />
      <v x="36.3078" y="9.2656" z="305.2285" u="0.5581" v="0.8238" nx="0" ny="0" nz="-1" />
      <t v1="69" v2="63" v3="68" />
      <v x="36.3078" y="9.2656" z="305.2285" u="0.5581" v="0.8238" nx="-0.0002" ny="0" nz="-1" />
      <t v1="65" v2="70" v3="67" />
      <v x="37.6983" y="11.0234" z="305.2285" u="0.3418" v="0.3253" nx="-0.0001" ny="0" nz="-1" />
      <v x="37.4302" y="11.8627" z="305.2285" u="0.3418" v="0.019" nx="-0.0001" ny="0" nz="-1" />
      <v x="38.9382" y="11.9201" z="305.2284" u="0.1293" v="0.0002" nx="-0.0001" ny="0" nz="-1" />
      <t v1="71" v2="72" v3="73" />
      <v x="39.0922" y="11.2359" z="305.2284" u="0.1076" v="0.2247" nx="-0.0001" ny="0" nz="-1" />
      <t v1="73" v2="74" v3="71" />
      <v x="37.7687" y="10.0635" z="305.2285" u="0.3418" v="0.6463" nx="-0.0001" ny="0" nz="-1" />
      <v x="37.6983" y="11.0234" z="305.2285" u="0.3418" v="0.3253" nx="-0.0001" ny="0" nz="-1" />
      <v x="39.0922" y="11.2359" z="305.2284" u="0.1076" v="0.2247" nx="-0.0001" ny="0" nz="-1" />
      <t v1="75" v2="76" v3="77" />
      <v x="39.0922" y="11.2359" z="305.2284" u="0.1076" v="0.2247" nx="-0.0001" ny="0" nz="-1" />
      <v x="39.7635" y="10.3531" z="305.2284" u="0.013" v="0.5144" nx="-0.0001" ny="0" nz="-1" />
      <v x="37.7687" y="10.0635" z="305.2285" u="0.3418" v="0.6463" nx="-0.0001" ny="0" nz="-1" />
      <t v1="78" v2="79" v3="80" />
      <v x="37.8427" y="9.264" z="305.2285" u="0.3418" v="0.8441" nx="-0.0001" ny="0" nz="-1" />
      <v x="37.7687" y="10.0635" z="305.2285" u="0.3418" v="0.6463" nx="-0.0001" ny="0" nz="-1" />
      <v x="39.7635" y="10.3531" z="305.2284" u="0.013" v="0.5144" nx="-0.0001" ny="0" nz="-1" />
      <t v1="81" v2="82" v3="83" />
      <v x="37.8427" y="9.264" z="305.2285" u="0.3418" v="0.8441" nx="0" ny="0" nz="-1" />
      <t v1="68" v2="84" v3="69" />
      <v x="33.4266" y="9.0008" z="305.229" u="0.906" v="0.9672" nx="-0.0002" ny="0.0001" nz="-1" />
      <v x="33.6136" y="9.4416" z="305.229" u="0.8796" v="0.8135" nx="-0.0002" ny="0.0001" nz="-1" />
      <v x="36.3078" y="9.2656" z="305.2285" u="0.5581" v="0.8238" nx="-0.0002" ny="0.0001" nz="-1" />
      <t v1="85" v2="86" v3="87" />
      <v x="36.3078" y="9.2656" z="305.2285" u="0.5581" v="0.8238" nx="-0.0423" ny="0.4583" nz="-0.8878" />
      <v x="36.2648" y="8.9967" z="305.0918" u="0.506" v="0.9495" nx="-0.0423" ny="0.4583" nz="-0.8878" />
      <v x="33.4266" y="9.0008" z="305.229" u="0.906" v="0.9672" nx="-0.0423" ny="0.4583" nz="-0.8878" />
      <t v1="88" v2="89" v3="90" />
      <v x="36.2648" y="8.9967" z="305.0918" u="0.506" v="0.9495" nx="0.0005" ny="0.4533" nz="-0.8914" />
      <v x="36.3078" y="9.2656" z="305.2285" u="0.5581" v="0.8238" nx="0.0005" ny="0.4533" nz="-0.8914" />
      <v x="37.8427" y="9.264" z="305.2285" u="0.3418" v="0.8441" nx="0.0005" ny="0.4533" nz="-0.8914" />
      <t v1="91" v2="92" v3="93" />
      <v x="37.8427" y="9.264" z="305.2285" u="0.3418" v="0.8441" nx="-0.0075" ny="0.4903" nz="-0.8715" />
      <v x="37.8635" y="8.9957" z="305.0774" u="0.2807" v="0.9554" nx="-0.0075" ny="0.4903" nz="-0.8715" />
      <v x="36.2648" y="8.9967" z="305.0918" u="0.506" v="0.9495" nx="-0.0075" ny="0.4903" nz="-0.8715" />
      <t v1="94" v2="95" v3="96" />
      <v x="37.8635" y="8.9957" z="305.0774" u="0.2807" v="0.9554" nx="-0.0402" ny="0.488" nz="-0.8719" />
      <v x="37.8427" y="9.264" z="305.2285" u="0.3418" v="0.8441" nx="-0.0402" ny="0.488" nz="-0.8719" />
      <v x="39.81" y="9.4261" z="305.2284" u="0.0064" v="0.8186" nx="-0.0402" ny="0.488" nz="-0.8719" />
      <t v1="97" v2="98" v3="99" />
      <v x="39.81" y="9.4261" z="305.2284" u="0.0064" v="0.8186" nx="-0.0001" ny="0" nz="-1" />
      <t v1="83" v2="100" v3="81" />
      <v x="39.81" y="9.4261" z="305.2284" u="0.0064" v="0.8186" nx="-0.0004" ny="0.3328" nz="-0.943" />
      <v x="39.9801" y="8.9956" z="305.0764" u="0.0024" v="0.956" nx="-0.0004" ny="0.3328" nz="-0.943" />
      <v x="37.8635" y="8.9957" z="305.0774" u="0.2807" v="0.9554" nx="-0.0004" ny="0.3328" nz="-0.943" />
      <t v1="101" v2="102" v3="103" />
      <v x="-13.6481" y="7.2676" z="70.109" u="0.7863" v="0.4643" nx="-0.1312" ny="0.9913" nz="0.0081" />
      <v x="-17.116" y="6.7866" z="72.8201" u="0.7164" v="0.5834" nx="-0.1312" ny="0.9913" nz="0.0081" />
      <v x="-17.116" y="6.7519" z="77.0868" u="0.1467" v="0.5834" nx="-0.1312" ny="0.9913" nz="0.0081" />
      <t v1="104" v2="105" v3="106" />
      <v x="-17.116" y="6.7519" z="77.0868" u="0.1467" v="0.5834" nx="-0.1299" ny="0.9915" nz="0.0087" />
      <v x="-13.6481" y="7.2257" z="74.8724" u="0.2166" v="0.4643" nx="-0.1299" ny="0.9915" nz="0.0087" />
      <v x="-13.6481" y="7.2676" z="70.109" u="0.7863" v="0.4643" nx="-0.1299" ny="0.9915" nz="0.0087" />
      <t v1="107" v2="108" v3="109" />
      <v x="-21.5839" y="6.6308" z="79.491" u="0.1127" v="0.7369" nx="-0.0227" ny="0.9997" nz="0.0081" />
      <v x="-17.116" y="6.7519" z="77.0868" u="0.1467" v="0.5834" nx="-0.0227" ny="0.9997" nz="0.0081" />
      <v x="-17.116" y="6.7866" z="72.8201" u="0.7164" v="0.5834" nx="-0.0227" ny="0.9997" nz="0.0081" />
      <t v1="110" v2="111" v3="112" />
      <v x="-17.116" y="6.7866" z="72.8201" u="0.7164" v="0.5834" nx="-0.0211" ny="0.9997" nz="0.0092" />
      <v x="-21.5839" y="6.6703" z="75.2242" u="0.6824" v="0.7369" nx="-0.0211" ny="0.9997" nz="0.0092" />
      <v x="-21.5839" y="6.6308" z="79.491" u="0.1127" v="0.7369" nx="-0.0211" ny="0.9997" nz="0.0092" />
      <t v1="113" v2="114" v3="115" />
      <v x="-28.6841" y="5.9468" z="79.6005" u="0.1429" v="0.9808" nx="-0.0957" ny="0.9954" nz="0.0092" />
      <v x="-21.5839" y="6.6308" z="79.491" u="0.1127" v="0.7369" nx="-0.0957" ny="0.9954" nz="0.0092" />
      <v x="-21.5839" y="6.6703" z="75.2242" u="0.6824" v="0.7369" nx="-0.0957" ny="0.9954" nz="0.0092" />
      <t v1="116" v2="117" v3="118" />
      <v x="-21.5839" y="6.6703" z="75.2242" u="0.6824" v="0.7369" nx="-0.1014" ny="0.9948" nz="0" />
      <v x="-28.6841" y="5.9468" z="75.6005" u="0.677" v="0.9808" nx="-0.1014" ny="0.9948" nz="0" />
      <v x="-28.6841" y="5.9468" z="79.6005" u="0.1429" v="0.9808" nx="-0.1014" ny="0.9948" nz="0" />
      <t v1="119" v2="120" v3="121" />
    </params>
  </meshfact>
</library>
