<library>
  <meshfact name="he_hangdao01_mesh_yicaibiand_21148">
    <plugin>genmeshfact</plugin>
    <zuse />
    <params>
      <material>Material_JoinedMaterial_#167_he_hangdao01</material>
      <v x="5.7534" y="-2.8737" z="-31.8824" u="0.0017" v="-2.0703" nx="0.0002" ny="1" nz="0.0002" />
      <v x="-2.9166" y="-2.8717" z="-31.8856" u="0.0008" v="2.3137" nx="0.0002" ny="1" nz="0.0002" />
      <v x="-2.9166" y="-2.8725" z="-28.2442" u="0.997" v="2.3138" nx="0.0002" ny="1" nz="0.0002" />
      <t v1="0" v2="1" v3="2" />
      <v x="5.7534" y="-2.8732" z="-30.972" u="0.2506" v="-2.0703" nx="-0.0001" ny="1" nz="-0.0006" />
      <v x="5.7534" y="-2.8737" z="-31.8824" u="0.0017" v="-2.0703" nx="-0.0001" ny="1" nz="-0.0006" />
      <v x="-2.9166" y="-2.8725" z="-28.2442" u="0.997" v="2.3138" nx="-0.0001" ny="1" nz="-0.0006" />
      <t v1="3" v2="4" v3="5" />
      <v x="5.7534" y="-2.8722" z="-29.2814" u="0.713" v="-2.0703" nx="-0.0001" ny="1" nz="-0.0006" />
      <v x="5.7534" y="-2.8732" z="-30.972" u="0.2506" v="-2.0703" nx="-0.0001" ny="1" nz="-0.0006" />
      <v x="-2.9166" y="-2.8725" z="-28.2442" u="0.997" v="2.3138" nx="-0.0001" ny="1" nz="-0.0006" />
      <t v1="6" v2="7" v3="8" />
      <v x="5.7534" y="-2.8716" z="-28.241" u="0.9976" v="-2.0703" nx="-0.0001" ny="1" nz="-0.0006" />
      <v x="5.7534" y="-2.8722" z="-29.2814" u="0.713" v="-2.0703" nx="-0.0001" ny="1" nz="-0.0006" />
      <t v1="9" v2="10" v3="5" />
      <v x="5.7534" y="-2.8732" z="-30.972" u="0.2506" v="-2.0703" nx="-0.0001" ny="1" nz="-0.0006" />
      <v x="5.7534" y="-2.8722" z="-29.2814" u="0.713" v="-2.0703" nx="-0.0001" ny="1" nz="-0.0006" />
      <v x="5.9424" y="-2.8722" z="-29.2813" u="0.7131" v="-2.2609" nx="-0.0001" ny="1" nz="-0.0006" />
      <t v1="11" v2="12" v3="13" />
      <v x="5.9424" y="-2.8722" z="-29.2813" u="0.7131" v="-2.2609" nx="0.0002" ny="1" nz="-0.0006" />
      <v x="5.9424" y="-2.8732" z="-30.9719" u="0.2507" v="-2.2609" nx="0.0002" ny="1" nz="-0.0006" />
      <v x="5.7534" y="-2.8732" z="-30.972" u="0.2506" v="-2.0703" nx="0.0002" ny="1" nz="-0.0006" />
      <t v1="14" v2="15" v3="16" />
      <v x="5.9424" y="-2.8722" z="-29.2813" u="0.7131" v="-2.2609" nx="0.0002" ny="1" nz="-0.0006" />
      <v x="5.9424" y="-2.8716" z="-28.2409" u="0.9976" v="-2.2609" nx="0.0002" ny="1" nz="-0.0006" />
      <v x="7.4189" y="-2.8741" z="-31.8817" u="0.0019" v="-3.0234" nx="0.0002" ny="1" nz="-0.0006" />
      <t v1="17" v2="18" v3="19" />
      <v x="5.9424" y="-2.8732" z="-30.9719" u="0.2507" v="-2.2609" nx="0.0002" ny="1" nz="-0.0006" />
      <v x="5.9424" y="-2.8722" z="-29.2813" u="0.7131" v="-2.2609" nx="0.0002" ny="1" nz="-0.0006" />
      <v x="7.4189" y="-2.8741" z="-31.8817" u="0.0019" v="-3.0234" nx="0.0002" ny="1" nz="-0.0006" />
      <t v1="20" v2="21" v3="22" />
      <v x="5.9424" y="-2.8737" z="-31.8823" u="0.0017" v="-2.2609" nx="0.0002" ny="1" nz="-0.0006" />
      <t v1="23" v2="20" v3="22" />
      <v x="5.9424" y="-2.8716" z="-28.2409" u="0.9976" v="-2.2609" nx="0.0005" ny="1" nz="-0.0005" />
      <v x="7.4189" y="-2.8724" z="-28.2416" u="0.9977" v="-3.0233" nx="0.0005" ny="1" nz="-0.0005" />
      <v x="7.4189" y="-2.8741" z="-31.8817" u="0.0019" v="-3.0234" nx="0.0005" ny="1" nz="-0.0005" />
      <t v1="24" v2="25" v3="26" />
      <v x="5.7534" y="-2.8725" z="17.6139" u="0.001" v="-2.0703" nx="0" ny="1" nz="-0.0002" />
      <v x="-2.9165" y="-2.8725" z="17.6118" u="0.0005" v="2.3137" nx="0" ny="1" nz="-0.0002" />
      <v x="-2.9166" y="-2.8717" z="21.2532" u="0.9967" v="2.3138" nx="0" ny="1" nz="-0.0002" />
      <t v1="27" v2="28" v3="29" />
      <v x="5.7534" y="-2.8718" z="18.5245" u="0.2502" v="-2.0703" nx="-0.0002" ny="1" nz="-0.0008" />
      <v x="5.7534" y="-2.8725" z="17.6139" u="0.001" v="-2.0703" nx="-0.0002" ny="1" nz="-0.0008" />
      <v x="-2.9166" y="-2.8717" z="21.2532" u="0.9967" v="2.3138" nx="-0.0002" ny="1" nz="-0.0008" />
      <t v1="30" v2="31" v3="32" />
      <v x="5.7534" y="-2.8705" z="20.2156" u="0.7128" v="-2.0703" nx="-0.0002" ny="1" nz="-0.0008" />
      <v x="5.7534" y="-2.8718" z="18.5245" u="0.2502" v="-2.0703" nx="-0.0002" ny="1" nz="-0.0008" />
      <v x="-2.9166" y="-2.8717" z="21.2532" u="0.9967" v="2.3138" nx="-0.0002" ny="1" nz="-0.0008" />
      <t v1="33" v2="34" v3="35" />
      <v x="5.7534" y="-2.8697" z="21.2563" u="0.9975" v="-2.0703" nx="-0.0002" ny="1" nz="-0.0008" />
      <t v1="36" v2="33" v3="35" />
      <v x="5.9425" y="-2.8704" z="20.2158" u="0.7129" v="-2.2609" nx="-0.0001" ny="1" nz="-0.0008" />
      <v x="5.9425" y="-2.8718" z="18.5246" u="0.2502" v="-2.2609" nx="-0.0001" ny="1" nz="-0.0008" />
      <v x="5.7534" y="-2.8718" z="18.5245" u="0.2502" v="-2.0703" nx="-0.0001" ny="1" nz="-0.0008" />
      <t v1="37" v2="38" v3="39" />
      <v x="5.7534" y="-2.8718" z="18.5245" u="0.2502" v="-2.0703" nx="-0.0003" ny="1" nz="-0.0008" />
      <v x="5.7534" y="-2.8705" z="20.2156" u="0.7128" v="-2.0703" nx="-0.0003" ny="1" nz="-0.0008" />
      <v x="5.9425" y="-2.8704" z="20.2158" u="0.7129" v="-2.2609" nx="-0.0003" ny="1" nz="-0.0008" />
      <t v1="40" v2="41" v3="42" />
      <v x="5.9425" y="-2.8704" z="20.2158" u="0.7129" v="-2.2609" nx="0" ny="1" nz="-0.0008" />
      <v x="5.9424" y="-2.8696" z="21.2564" u="0.9976" v="-2.2609" nx="0" ny="1" nz="-0.0008" />
      <v x="7.419" y="-2.8725" z="17.6143" u="0.0012" v="-3.0234" nx="0" ny="1" nz="-0.0008" />
      <t v1="43" v2="44" v3="45" />
      <v x="5.9425" y="-2.8718" z="18.5246" u="0.2502" v="-2.2609" nx="0" ny="1" nz="-0.0008" />
      <t v1="46" v2="43" v3="45" />
      <v x="5.9425" y="-2.8725" z="17.614" u="0.0011" v="-2.2609" nx="0" ny="1" nz="-0.0008" />
      <t v1="47" v2="46" v3="45" />
      <v x="5.9424" y="-2.8696" z="21.2564" u="0.9976" v="-2.2609" nx="-0.0002" ny="1" nz="-0.0009" />
      <v x="7.4189" y="-2.8692" z="21.257" u="0.9977" v="-3.0233" nx="-0.0002" ny="1" nz="-0.0009" />
      <v x="7.419" y="-2.8725" z="17.6143" u="0.0012" v="-3.0234" nx="-0.0002" ny="1" nz="-0.0009" />
      <t v1="48" v2="49" v3="50" />
      <v x="-7.4189" y="-2.8747" z="21.2466" u="0.0005" v="1.4283" nx="-0.0007" ny="1" nz="-0.0002" />
      <v x="-2.9166" y="-2.8717" z="21.2532" u="1.2995" v="1.4323" nx="-0.0007" ny="1" nz="-0.0002" />
      <v x="-2.9165" y="-2.8725" z="17.6118" u="1.2995" v="-0.713" nx="-0.0007" ny="1" nz="-0.0002" />
      <t v1="51" v2="52" v3="53" />
      <v x="-2.9165" y="-2.8725" z="17.6118" u="1.2995" v="-0.713" nx="0" ny="1" nz="0.0006" />
      <v x="-7.4188" y="-2.8724" z="17.6104" u="0.0005" v="-0.7139" nx="0" ny="1" nz="0.0006" />
      <v x="-7.4189" y="-2.8747" z="21.2466" u="0.0005" v="1.4283" nx="0" ny="1" nz="0.0006" />
      <t v1="54" v2="55" v3="56" />
      <v x="-7.4188" y="-2.8724" z="17.6104" u="0.0005" v="-0.7139" nx="0" ny="1" nz="0" />
      <v x="-2.9165" y="-2.8725" z="17.6118" u="1.2995" v="-0.713" nx="0" ny="1" nz="0" />
      <v x="-2.9166" y="-2.8725" z="-28.2442" u="1.2995" v="-19.1559" nx="0" ny="1" nz="0" />
      <t v1="57" v2="58" v3="59" />
      <v x="-7.4189" y="-2.8747" z="21.2466" u="0.0005" v="1.4283" nx="-0.0007" ny="1" nz="0" />
      <v x="-7.4189" y="-2.8747" z="26.797" u="0.0005" v="4.6982" nx="-0.0007" ny="1" nz="0" />
      <v x="-2.9166" y="-2.8717" z="21.2532" u="1.2995" v="1.4323" nx="-0.0007" ny="1" nz="0" />
      <t v1="60" v2="61" v3="62" />
      <v x="-4.0422" y="-2.8724" z="26.802" u="0.9747" v="4.7013" nx="-0.0007" ny="1" nz="0" />
      <v x="-2.9166" y="-2.8717" z="26.8036" u="1.2995" v="4.7023" nx="-0.0007" ny="1" nz="0" />
      <t v1="63" v2="64" v3="62" />
      <v x="-6.2933" y="-2.8739" z="26.7986" u="0.3252" v="4.6993" nx="-0.0007" ny="1" nz="0" />
      <t v1="65" v2="63" v3="62" />
      <t v1="61" v2="65" v3="62" />
      <v x="-2.9166" y="-2.8725" z="-28.2442" u="1.2995" v="-19.1559" nx="-0.0001" ny="1" nz="0" />
      <v x="-7.4189" y="-2.8731" z="-28.2498" u="0.0005" v="-19.1593" nx="-0.0001" ny="1" nz="0" />
      <v x="-7.4188" y="-2.8724" z="17.6104" u="0.0005" v="-0.7139" nx="-0.0001" ny="1" nz="0" />
      <t v1="66" v2="67" v3="68" />
      <v x="-7.4189" y="-2.8731" z="-28.2498" u="0.0005" v="-19.1593" nx="-0.0001" ny="1" nz="0.0002" />
      <v x="-2.9166" y="-2.8725" z="-28.2442" u="1.2995" v="-19.1559" nx="-0.0001" ny="1" nz="0.0002" />
      <v x="-2.9166" y="-2.8717" z="-31.8856" u="1.2995" v="-21.3012" nx="-0.0001" ny="1" nz="0.0002" />
      <t v1="69" v2="70" v3="71" />
      <v x="-2.9166" y="-2.8717" z="-31.8856" u="1.2995" v="-21.3012" nx="0.0005" ny="1" nz="0.0011" />
      <v x="-7.4189" y="-2.8692" z="-31.8886" u="0.0005" v="-21.3031" nx="0.0005" ny="1" nz="0.0011" />
      <v x="-7.4189" y="-2.8731" z="-28.2498" u="0.0005" v="-19.1593" nx="0.0005" ny="1" nz="0.0011" />
      <t v1="72" v2="73" v3="74" />
      <v x="-6.2919" y="-2.8754" z="27.1784" u="0.2502" v="0.925" nx="-0.002" ny="1" nz="-0.0003" />
      <v x="-7.416" y="-2.8775" z="27.1767" u="0.0008" v="0.9253" nx="-0.002" ny="1" nz="-0.0003" />
      <v x="-7.4174" y="-2.8761" z="31.882" u="0.0005" v="0.0018" nx="-0.002" ny="1" nz="-0.0003" />
      <t v1="75" v2="76" v3="77" />
      <v x="-4.0406" y="-2.8739" z="27.1817" u="0.7495" v="0.9243" nx="-0.0007" ny="1" nz="0" />
      <v x="-6.2919" y="-2.8754" z="27.1784" u="0.2502" v="0.925" nx="-0.0007" ny="1" nz="0" />
      <v x="-7.4174" y="-2.8761" z="31.882" u="0.0005" v="0.0018" nx="-0.0007" ny="1" nz="0" />
      <t v1="78" v2="79" v3="80" />
      <v x="-2.9136" y="-2.8745" z="27.1834" u="0.9995" v="0.924" nx="0.0006" ny="1" nz="0.0009" />
      <v x="-4.0406" y="-2.8739" z="27.1817" u="0.7495" v="0.9243" nx="0.0006" ny="1" nz="0.0009" />
      <v x="-7.4174" y="-2.8761" z="31.882" u="0.0005" v="0.0018" nx="0.0006" ny="1" nz="0.0009" />
      <t v1="81" v2="82" v3="83" />
      <v x="-2.9151" y="-2.8731" z="31.8886" u="0.9992" v="0.0005" nx="-0.0007" ny="1" nz="-0.0003" />
      <v x="-2.9136" y="-2.8745" z="27.1834" u="0.9995" v="0.924" nx="-0.0007" ny="1" nz="-0.0003" />
      <v x="-7.4174" y="-2.8761" z="31.882" u="0.0005" v="0.0018" nx="-0.0007" ny="1" nz="-0.0003" />
      <t v1="84" v2="85" v3="86" />
      <v x="-6.2933" y="-2.8739" z="26.7986" u="0.2498" v="0.9995" nx="-0.0007" ny="1" nz="0.0038" />
      <v x="-6.2919" y="-2.8754" z="27.1784" u="0.2502" v="0.925" nx="-0.0007" ny="1" nz="0.0038" />
      <v x="-4.0406" y="-2.8739" z="27.1817" u="0.7495" v="0.9243" nx="-0.0007" ny="1" nz="0.0038" />
      <t v1="87" v2="88" v3="89" />
      <v x="-4.0406" y="-2.8739" z="27.1817" u="0.7495" v="0.9243" nx="-0.0007" ny="1" nz="0.0038" />
      <v x="-4.0422" y="-2.8724" z="26.802" u="0.7492" v="0.9988" nx="-0.0007" ny="1" nz="0.0038" />
      <v x="-6.2933" y="-2.8739" z="26.7986" u="0.2498" v="0.9995" nx="-0.0007" ny="1" nz="0.0038" />
      <t v1="90" v2="91" v3="92" />
    </params>
  </meshfact>
</library>
