<library>
  <meshfact name="he_pidai02_mesh_Object19_3171">
    <plugin>genmeshfact</plugin>
    <zuse />
    <params>
      <material>Material_JoinedMaterial_#143_he_pidai02</material>
      <v x="0.4397" y="-0.6396" z="-0.001" u="-3.6715" v="1" nx="0.0001" ny="-0.9998" nz="-0.0203" />
      <v x="-0.4637" y="-0.6397" z="-0.001" u="-3.6715" v="0" nx="0.0001" ny="-0.9998" nz="-0.0203" />
      <v x="-0.4628" y="0.563" z="-59.1272" u="-13.7953" v="0" nx="0.0001" ny="-0.9998" nz="-0.0203" />
      <t v1="0" v2="1" v3="2" />
      <v x="-0.4628" y="0.563" z="-59.1272" u="-13.7953" v="0" nx="0.0001" ny="-0.9998" nz="-0.0203" />
      <v x="0.4471" y="0.5631" z="-59.1268" u="-13.7953" v="1" nx="0.0001" ny="-0.9998" nz="-0.0203" />
      <v x="0.4397" y="-0.6396" z="-0.001" u="-3.6715" v="1" nx="0.0001" ny="-0.9998" nz="-0.0203" />
      <t v1="3" v2="4" v3="5" />
      <v x="-0.2303" y="0.9251" z="-59.1274" u="-13.7192" v="0.2555" nx="0.5339" ny="0.8454" nz="0.0172" />
      <v x="-0.4628" y="1.0719" z="-59.1276" u="-13.7192" v="0" nx="0.5339" ny="0.8454" nz="0.0172" />
      <v x="-0.4637" y="-0.1308" z="-0.0015" u="71.4384" v="0" nx="0.5339" ny="0.8454" nz="0.0172" />
      <t v1="6" v2="7" v3="8" />
      <v x="-0.4637" y="-0.1308" z="-0.0015" u="71.4384" v="0" nx="0.534" ny="0.8453" nz="0.0172" />
      <v x="-0.2313" y="-0.2777" z="-0.0015" u="71.4384" v="0.2555" nx="0.534" ny="0.8453" nz="0.0172" />
      <v x="-0.2303" y="0.9251" z="-59.1274" u="-13.7192" v="0.2555" nx="0.534" ny="0.8453" nz="0.0172" />
      <t v1="9" v2="10" v3="11" />
      <v x="-0.0078" y="0.9185" z="-59.1272" u="-13.7192" v="0.5" nx="0.0292" ny="0.9994" nz="0.0203" />
      <v x="-0.2303" y="0.9251" z="-59.1274" u="-13.7192" v="0.2555" nx="0.0292" ny="0.9994" nz="0.0203" />
      <v x="-0.2313" y="-0.2777" z="-0.0015" u="71.4384" v="0.2555" nx="0.0292" ny="0.9994" nz="0.0203" />
      <t v1="12" v2="13" v3="14" />
      <v x="-0.0088" y="-0.2842" z="-0.0012" u="71.4384" v="0.5" nx="0.0292" ny="0.9994" nz="0.0203" />
      <t v1="14" v2="15" v3="12" />
      <v x="0.2147" y="0.9251" z="-59.1273" u="-13.7192" v="0.7445" nx="-0.0293" ny="0.9994" nz="0.0203" />
      <v x="-0.0078" y="0.9185" z="-59.1272" u="-13.7192" v="0.5" nx="-0.0293" ny="0.9994" nz="0.0203" />
      <v x="-0.0088" y="-0.2842" z="-0.0012" u="71.4384" v="0.5" nx="-0.0293" ny="0.9994" nz="0.0203" />
      <t v1="16" v2="17" v3="18" />
      <v x="-0.0088" y="-0.2842" z="-0.0012" u="71.4384" v="0.5" nx="-0.0294" ny="0.9994" nz="0.0203" />
      <v x="0.2138" y="-0.2776" z="-0.0013" u="71.4384" v="0.7445" nx="-0.0294" ny="0.9994" nz="0.0203" />
      <v x="0.2147" y="0.9251" z="-59.1273" u="-13.7192" v="0.7445" nx="-0.0294" ny="0.9994" nz="0.0203" />
      <t v1="19" v2="20" v3="21" />
      <v x="0.4471" y="1.0719" z="-59.1273" u="-13.7192" v="1" nx="-0.534" ny="0.8453" nz="0.0172" />
      <v x="0.2147" y="0.9251" z="-59.1273" u="-13.7192" v="0.7445" nx="-0.534" ny="0.8453" nz="0.0172" />
      <v x="0.2138" y="-0.2776" z="-0.0013" u="-3.7476" v="0.7445" nx="-0.534" ny="0.8453" nz="0.0172" />
      <t v1="22" v2="23" v3="24" />
      <v x="0.2138" y="-0.2776" z="-0.0013" u="-3.7476" v="0.7445" nx="-0.534" ny="0.8453" nz="0.0172" />
      <v x="0.4463" y="-0.1308" z="-0.0013" u="-3.7476" v="1" nx="-0.534" ny="0.8453" nz="0.0172" />
      <v x="0.4471" y="1.0719" z="-59.1273" u="-13.7192" v="1" nx="-0.534" ny="0.8453" nz="0.0172" />
      <t v1="25" v2="26" v3="27" />
      <v x="0.4447" y="-0.648" z="19.7098" u="-10.4207" v="1" nx="0.0001" ny="-1" nz="0.0002" />
      <v x="0.4397" y="-0.6396" z="59.1271" u="-3.6715" v="1" nx="0.0001" ny="-1" nz="0.0002" />
      <v x="-0.4636" y="-0.6397" z="59.1271" u="-3.6715" v="0" nx="0.0001" ny="-1" nz="0.0002" />
      <t v1="28" v2="29" v3="30" />
      <v x="-0.4636" y="-0.6397" z="59.1271" u="-3.6715" v="0" nx="0.0001" ny="-1" nz="0.0002" />
      <v x="-0.4631" y="-0.6481" z="19.7096" u="-10.4207" v="0" nx="0.0001" ny="-1" nz="0.0002" />
      <v x="0.4447" y="-0.648" z="19.7098" u="-10.4207" v="1" nx="0.0001" ny="-1" nz="0.0002" />
      <t v1="31" v2="32" v3="33" />
      <v x="-0.4631" y="-0.1393" z="19.7092" u="14.6666" v="0" nx="0.5342" ny="0.8454" nz="-0.0002" />
      <v x="-0.4636" y="-0.1309" z="59.1266" u="71.4384" v="0" nx="0.5342" ny="0.8454" nz="-0.0002" />
      <v x="-0.2313" y="-0.2777" z="59.1266" u="71.4384" v="0.2555" nx="0.5342" ny="0.8454" nz="-0.0002" />
      <t v1="34" v2="35" v3="36" />
      <v x="-0.2313" y="-0.2777" z="59.1266" u="71.4384" v="0.2555" nx="0.5341" ny="0.8454" nz="-0.0002" />
      <v x="-0.2307" y="-0.2861" z="19.7092" u="14.6666" v="0.2555" nx="0.5341" ny="0.8454" nz="-0.0002" />
      <v x="-0.4631" y="-0.1393" z="19.7092" u="14.6666" v="0" nx="0.5341" ny="0.8454" nz="-0.0002" />
      <t v1="37" v2="38" v3="39" />
      <v x="-0.2307" y="-0.2861" z="19.7092" u="14.6666" v="0.2555" nx="0.0292" ny="0.9996" nz="-0.0002" />
      <v x="-0.2313" y="-0.2777" z="59.1266" u="71.4384" v="0.2555" nx="0.0292" ny="0.9996" nz="-0.0002" />
      <v x="-0.0088" y="-0.2842" z="59.1268" u="71.4384" v="0.5" nx="0.0292" ny="0.9996" nz="-0.0002" />
      <t v1="40" v2="41" v3="42" />
      <v x="-0.0081" y="-0.2926" z="19.7095" u="14.6666" v="0.5" nx="0.0292" ny="0.9996" nz="-0.0002" />
      <t v1="42" v2="43" v3="40" />
      <v x="-0.0081" y="-0.2926" z="19.7095" u="14.6666" v="0.5" nx="-0.0293" ny="0.9996" nz="-0.0002" />
      <v x="-0.0088" y="-0.2842" z="59.1268" u="71.4384" v="0.5" nx="-0.0293" ny="0.9996" nz="-0.0002" />
      <v x="0.2139" y="-0.2777" z="59.1267" u="71.4384" v="0.7445" nx="-0.0293" ny="0.9996" nz="-0.0002" />
      <t v1="44" v2="45" v3="46" />
      <v x="0.2139" y="-0.2777" z="59.1267" u="71.4384" v="0.7445" nx="-0.0294" ny="0.9996" nz="-0.0002" />
      <v x="0.2144" y="-0.286" z="19.7095" u="14.6666" v="0.7445" nx="-0.0294" ny="0.9996" nz="-0.0002" />
      <v x="-0.0081" y="-0.2926" z="19.7095" u="14.6666" v="0.5" nx="-0.0294" ny="0.9996" nz="-0.0002" />
      <t v1="47" v2="48" v3="49" />
      <v x="0.2144" y="-0.286" z="19.7095" u="-10.3954" v="0.7445" nx="-0.5342" ny="0.8453" nz="-0.0002" />
      <v x="0.2139" y="-0.2777" z="59.1267" u="-3.7476" v="0.7445" nx="-0.5342" ny="0.8453" nz="-0.0002" />
      <v x="0.4463" y="-0.1308" z="59.1267" u="-3.7476" v="1" nx="-0.5342" ny="0.8453" nz="-0.0002" />
      <t v1="50" v2="51" v3="52" />
      <v x="0.4463" y="-0.1308" z="59.1267" u="-3.7476" v="1" nx="-0.534" ny="0.8455" nz="-0.0002" />
      <v x="0.4469" y="-0.1392" z="19.7094" u="-10.3954" v="1" nx="-0.534" ny="0.8455" nz="-0.0002" />
      <v x="0.2144" y="-0.286" z="19.7095" u="-10.3954" v="0.7445" nx="-0.534" ny="0.8455" nz="-0.0002" />
      <t v1="53" v2="54" v3="55" />
    </params>
  </meshfact>
</library>
