<library>
  <meshfact name="jingxiachaoshi_mesh_jingxiasha_111">
    <plugin>genmeshfact</plugin>
    <zuse />
    <params>
      <material>Material_u_0283_jingxiachaoshi</material>
      <v x="-592.2805" y="-190.3338" z="91.134" u="1.0019" v="1" nx="0.9445" ny="0" nz="0.3285" />
      <v x="-591.7288" y="-190.3338" z="89.548" u="0.0015" v="1" nx="0.9445" ny="0" nz="0.3285" />
      <v x="-591.7285" y="-189.9642" z="89.5473" u="0.0006" v="0" nx="0.9445" ny="0" nz="0.3285" />
      <t v1="0" v2="1" v3="2" />
      <v x="-591.7285" y="-189.9642" z="89.5473" u="0.0006" v="0" nx="0.9445" ny="0" nz="0.3285" />
      <v x="-592.2805" y="-189.9604" z="91.134" u="1.0014" v="0" nx="0.9445" ny="0" nz="0.3285" />
      <v x="-592.2805" y="-190.3338" z="91.134" u="1.0019" v="1" nx="0.9445" ny="0" nz="0.3285" />
      <t v1="3" v2="4" v3="5" />
    </params>
  </meshfact>
</library>
