<library>
  <meshfact name="jingxiachaoshi_mesh_jingxiasha_118">
    <plugin>genmeshfact</plugin>
    <zuse />
    <params>
      <material>Material_u_0310_jingxiachaoshi</material>
      <v x="-589.8174" y="-192.3133" z="92.62" u="-2.4344" v="-0.1003" nx="0.327" ny="0.0202" nz="-0.9448" />
      <v x="-589.7008" y="-192.3133" z="92.6604" u="-1.8978" v="-0.1003" nx="0.327" ny="0.0202" nz="-0.9448" />
      <v x="-589.699" y="-192.611" z="92.6546" u="-1.8985" v="0.4153" nx="0.327" ny="0.0202" nz="-0.9448" />
      <t v1="0" v2="1" v3="2" />
      <v x="-589.699" y="-192.611" z="92.6546" u="-1.8985" v="0.4153" nx="0.3271" ny="0.0203" nz="-0.9448" />
      <v x="-589.8156" y="-192.611" z="92.6142" u="-2.4351" v="0.4153" nx="0.3271" ny="0.0203" nz="-0.9448" />
      <v x="-589.8174" y="-192.3133" z="92.62" u="-2.4344" v="-0.1003" nx="0.3271" ny="0.0203" nz="-0.9448" />
      <t v1="3" v2="4" v3="5" />
      <v x="-589.7869" y="-192.8855" z="92.5321" u="-2.4344" v="0.8905" nx="0.3119" ny="0.3022" nz="-0.9008" />
      <v x="-589.8156" y="-192.611" z="92.6142" u="-2.4351" v="0.4153" nx="0.3119" ny="0.3022" nz="-0.9008" />
      <v x="-589.699" y="-192.611" z="92.6546" u="-1.8985" v="0.4153" nx="0.3119" ny="0.3022" nz="-0.9008" />
      <t v1="6" v2="7" v3="8" />
      <v x="-589.7551" y="-192.8855" z="92.5431" u="-2.2885" v="0.8905" nx="0.3116" ny="0.3023" nz="-0.9008" />
      <v x="-589.7869" y="-192.8855" z="92.5321" u="-2.4344" v="0.8905" nx="0.3116" ny="0.3023" nz="-0.9008" />
      <v x="-589.699" y="-192.611" z="92.6546" u="-1.8985" v="0.4153" nx="0.3116" ny="0.3023" nz="-0.9008" />
      <t v1="9" v2="10" v3="11" />
      <v x="-589.6443" y="-192.8855" z="92.5815" u="-1.7785" v="0.8905" nx="0.312" ny="0.3021" nz="-0.9007" />
      <v x="-589.7551" y="-192.8855" z="92.5431" u="-2.2885" v="0.8905" nx="0.312" ny="0.3021" nz="-0.9007" />
      <v x="-589.699" y="-192.611" z="92.6546" u="-1.8985" v="0.4153" nx="0.312" ny="0.3021" nz="-0.9007" />
      <t v1="12" v2="13" v3="14" />
      <v x="-589.7551" y="-192.8855" z="92.5431" u="-2.2885" v="0.8905" nx="0.3014" ny="0.3905" nz="-0.8699" />
      <v x="-589.6443" y="-192.8855" z="92.5815" u="-1.7785" v="0.8905" nx="0.3014" ny="0.3905" nz="-0.8699" />
      <v x="-589.6274" y="-193.0066" z="92.533" u="-1.7785" v="1.1003" nx="0.3014" ny="0.3905" nz="-0.8699" />
      <t v1="15" v2="16" v3="17" />
      <v x="-589.6274" y="-193.0066" z="92.533" u="-1.7785" v="1.1003" nx="0.3012" ny="0.3903" nz="-0.87" />
      <v x="-589.7383" y="-193.0066" z="92.4946" u="-2.2885" v="1.1003" nx="0.3012" ny="0.3903" nz="-0.87" />
      <v x="-589.7551" y="-192.8855" z="92.5431" u="-2.2885" v="0.8905" nx="0.3012" ny="0.3903" nz="-0.87" />
      <t v1="18" v2="19" v3="20" />
      <v x="-588.5398" y="-192.611" z="93.0559" u="3.4351" v="0.4153" nx="0.3271" ny="0.0202" nz="-0.9448" />
      <v x="-588.6564" y="-192.611" z="93.0156" u="2.8985" v="0.4153" nx="0.3271" ny="0.0202" nz="-0.9448" />
      <v x="-588.6584" y="-192.3133" z="93.0212" u="2.8983" v="-0.1003" nx="0.3271" ny="0.0202" nz="-0.9448" />
      <t v1="21" v2="22" v3="23" />
      <v x="-588.5418" y="-192.3133" z="93.0616" u="3.4349" v="-0.1003" nx="0.3271" ny="0.0202" nz="-0.9448" />
      <t v1="23" v2="24" v3="21" />
      <v x="-588.6537" y="-192.8855" z="92.9244" u="2.7795" v="0.8905" nx="0.3119" ny="0.3022" nz="-0.9008" />
      <v x="-588.6564" y="-192.611" z="93.0156" u="2.8985" v="0.4153" nx="0.3119" ny="0.3022" nz="-0.9008" />
      <v x="-588.5398" y="-192.611" z="93.0559" u="3.4351" v="0.4153" nx="0.3119" ny="0.3022" nz="-0.9008" />
      <t v1="25" v2="26" v3="27" />
      <v x="-588.5429" y="-192.8855" z="92.9628" u="3.2894" v="0.8905" nx="0.312" ny="0.3021" nz="-0.9008" />
      <v x="-588.6537" y="-192.8855" z="92.9244" u="2.7795" v="0.8905" nx="0.312" ny="0.3021" nz="-0.9008" />
      <v x="-588.5398" y="-192.611" z="93.0559" u="3.4351" v="0.4153" nx="0.312" ny="0.3021" nz="-0.9008" />
      <t v1="28" v2="29" v3="30" />
      <v x="-588.5113" y="-192.8855" z="92.9738" u="3.4349" v="0.8905" nx="0.3119" ny="0.3021" nz="-0.9008" />
      <v x="-588.5429" y="-192.8855" z="92.9628" u="3.2894" v="0.8905" nx="0.3119" ny="0.3021" nz="-0.9008" />
      <v x="-588.5398" y="-192.611" z="93.0559" u="3.4351" v="0.4153" nx="0.3119" ny="0.3021" nz="-0.9008" />
      <t v1="31" v2="32" v3="33" />
      <v x="-588.526" y="-193.0066" z="92.9143" u="3.2894" v="1.1003" nx="0.3012" ny="0.3903" nz="-0.87" />
      <v x="-588.6368" y="-193.0066" z="92.8759" u="2.7795" v="1.1003" nx="0.3012" ny="0.3903" nz="-0.87" />
      <v x="-588.6537" y="-192.8855" z="92.9244" u="2.7795" v="0.8905" nx="0.3012" ny="0.3903" nz="-0.87" />
      <t v1="34" v2="35" v3="36" />
      <v x="-588.6537" y="-192.8855" z="92.9244" u="2.7795" v="0.8905" nx="0.3013" ny="0.3904" nz="-0.8699" />
      <v x="-588.5429" y="-192.8855" z="92.9628" u="3.2894" v="0.8905" nx="0.3013" ny="0.3904" nz="-0.8699" />
      <v x="-588.526" y="-193.0066" z="92.9143" u="3.2894" v="1.1003" nx="0.3013" ny="0.3904" nz="-0.8699" />
      <t v1="37" v2="38" v3="39" />
      <v x="-591.1024" y="-192.3133" z="92.1751" u="-2.4344" v="-0.1003" nx="0.3272" ny="0.0203" nz="-0.9447" />
      <v x="-590.9858" y="-192.3133" z="92.2155" u="-1.8978" v="-0.1003" nx="0.3272" ny="0.0203" nz="-0.9447" />
      <v x="-590.9839" y="-192.611" z="92.2097" u="-1.8985" v="0.4153" nx="0.3272" ny="0.0203" nz="-0.9447" />
      <t v1="40" v2="41" v3="42" />
      <v x="-590.9839" y="-192.611" z="92.2097" u="-1.8985" v="0.4153" nx="0.3271" ny="0.0203" nz="-0.9448" />
      <v x="-591.1005" y="-192.611" z="92.1693" u="-2.4351" v="0.4153" nx="0.3271" ny="0.0203" nz="-0.9448" />
      <v x="-591.1024" y="-192.3133" z="92.1751" u="-2.4344" v="-0.1003" nx="0.3271" ny="0.0203" nz="-0.9448" />
      <t v1="43" v2="44" v3="45" />
      <v x="-591.0718" y="-192.8855" z="92.0872" u="-2.4344" v="0.8905" nx="0.3119" ny="0.3021" nz="-0.9008" />
      <v x="-591.1005" y="-192.611" z="92.1693" u="-2.4351" v="0.4153" nx="0.3119" ny="0.3021" nz="-0.9008" />
      <v x="-590.9839" y="-192.611" z="92.2097" u="-1.8985" v="0.4153" nx="0.3119" ny="0.3021" nz="-0.9008" />
      <t v1="46" v2="47" v3="48" />
      <v x="-591.0401" y="-192.8855" z="92.0982" u="-2.2885" v="0.8905" nx="0.3116" ny="0.3022" nz="-0.9009" />
      <v x="-591.0718" y="-192.8855" z="92.0872" u="-2.4344" v="0.8905" nx="0.3116" ny="0.3022" nz="-0.9009" />
      <v x="-590.9839" y="-192.611" z="92.2097" u="-1.8985" v="0.4153" nx="0.3116" ny="0.3022" nz="-0.9009" />
      <t v1="49" v2="50" v3="51" />
      <v x="-590.9293" y="-192.8855" z="92.1366" u="-1.7785" v="0.8905" nx="0.3119" ny="0.3021" nz="-0.9008" />
      <v x="-591.0401" y="-192.8855" z="92.0982" u="-2.2885" v="0.8905" nx="0.3119" ny="0.3021" nz="-0.9008" />
      <v x="-590.9839" y="-192.611" z="92.2097" u="-1.8985" v="0.4153" nx="0.3119" ny="0.3021" nz="-0.9008" />
      <t v1="52" v2="53" v3="54" />
      <v x="-591.0401" y="-192.8855" z="92.0982" u="-2.2885" v="0.8905" nx="0.3012" ny="0.3905" nz="-0.87" />
      <v x="-590.9293" y="-192.8855" z="92.1366" u="-1.7785" v="0.8905" nx="0.3012" ny="0.3905" nz="-0.87" />
      <v x="-590.9124" y="-193.0066" z="92.0881" u="-1.7785" v="1.1003" nx="0.3012" ny="0.3905" nz="-0.87" />
      <t v1="55" v2="56" v3="57" />
      <v x="-590.9124" y="-193.0066" z="92.0881" u="-1.7785" v="1.1003" nx="0.3012" ny="0.3904" nz="-0.87" />
      <v x="-591.0232" y="-193.0066" z="92.0497" u="-2.2885" v="1.1003" nx="0.3012" ny="0.3904" nz="-0.87" />
      <v x="-591.0401" y="-192.8855" z="92.0982" u="-2.2885" v="0.8905" nx="0.3012" ny="0.3904" nz="-0.87" />
      <t v1="58" v2="59" v3="60" />
      <v x="-589.8247" y="-192.611" z="92.6111" u="3.4351" v="0.4153" nx="0.3271" ny="0.0202" nz="-0.9448" />
      <v x="-589.9413" y="-192.611" z="92.5707" u="2.8985" v="0.4153" nx="0.3271" ny="0.0202" nz="-0.9448" />
      <v x="-589.9434" y="-192.3133" z="92.5764" u="2.8983" v="-0.1003" nx="0.3271" ny="0.0202" nz="-0.9448" />
      <t v1="61" v2="62" v3="63" />
      <v x="-589.9434" y="-192.3133" z="92.5764" u="2.8983" v="-0.1003" nx="0.3273" ny="0.0203" nz="-0.9447" />
      <v x="-589.8268" y="-192.3133" z="92.6168" u="3.4349" v="-0.1003" nx="0.3273" ny="0.0203" nz="-0.9447" />
      <v x="-589.8247" y="-192.611" z="92.6111" u="3.4351" v="0.4153" nx="0.3273" ny="0.0203" nz="-0.9447" />
      <t v1="64" v2="65" v3="66" />
      <v x="-589.9387" y="-192.8855" z="92.4796" u="2.7795" v="0.8905" nx="0.3119" ny="0.3021" nz="-0.9008" />
      <v x="-589.9413" y="-192.611" z="92.5707" u="2.8985" v="0.4153" nx="0.3119" ny="0.3021" nz="-0.9008" />
      <v x="-589.8247" y="-192.611" z="92.6111" u="3.4351" v="0.4153" nx="0.3119" ny="0.3021" nz="-0.9008" />
      <t v1="67" v2="68" v3="69" />
      <v x="-589.8278" y="-192.8855" z="92.5179" u="3.2894" v="0.8905" nx="0.3119" ny="0.3021" nz="-0.9008" />
      <t v1="70" v2="67" v3="69" />
      <v x="-589.7962" y="-192.8855" z="92.5289" u="3.4349" v="0.8905" nx="0.3117" ny="0.3021" nz="-0.9009" />
      <v x="-589.8278" y="-192.8855" z="92.5179" u="3.2894" v="0.8905" nx="0.3117" ny="0.3021" nz="-0.9009" />
      <v x="-589.8247" y="-192.611" z="92.6111" u="3.4351" v="0.4153" nx="0.3117" ny="0.3021" nz="-0.9009" />
      <t v1="71" v2="72" v3="73" />
      <v x="-589.8109" y="-193.0066" z="92.4694" u="3.2894" v="1.1003" nx="0.3012" ny="0.3905" nz="-0.87" />
      <v x="-589.9218" y="-193.0066" z="92.431" u="2.7795" v="1.1003" nx="0.3012" ny="0.3905" nz="-0.87" />
      <v x="-589.9387" y="-192.8855" z="92.4796" u="2.7795" v="0.8905" nx="0.3012" ny="0.3905" nz="-0.87" />
      <t v1="74" v2="75" v3="76" />
      <v x="-589.8278" y="-192.8855" z="92.5179" u="3.2894" v="0.8905" nx="0.3012" ny="0.3905" nz="-0.87" />
      <t v1="76" v2="77" v3="74" />
    </params>
  </meshfact>
</library>
